LICENCE
README.md
setup.py
almaviva.egg-info/PKG-INFO
almaviva.egg-info/SOURCES.txt
almaviva.egg-info/dependency_links.txt
almaviva.egg-info/requires.txt
almaviva.egg-info/top_level.txt
almaviva/database/__init__.py
almaviva/file/__init__.py
almaviva/ihm/__init__.py
almaviva/logging/__init__.py
almaviva/webdriver/__init__.py