Metadata-Version: 2.1
Name: almaviva
Version: 1.4.8
Summary: Biblioteca com funções personalizadas desenvolvidos para Almaviva Do Brasil
Home-page: http://workflow.almavivadobrasil.com.br:8000/almaviva-library
Author: Assad, Felipe
Author-email: fassad@almavivadobrasil.com.br
License: Almaviva do Brasil Licence
Keywords: almavivadobrasil,database,logging,file,ihm,webdriver
Platform: UNKNOWN
